<ROOT>
  <CONTENTS>
    <CONTENT No="001" Type="" Group="1">
      <FIELD1 Name="e_001">Something unthinkable has occurred.</FIELD1>
      <FIELD2 Name="k_001">생각 할 수 없는 어떤 것이 일어 났다.</FIELD2>
      <DESC>sth(~thing) 혹은 sb(~body)  뒤 후치수식</DESC>
    </CONTENT>
    <CONTENT No="003" Type="" Group="1">
      <FIELD1 Name="e_003">Birds sing.</FIELD1>
      <FIELD2 Name="k_003">새들은 노래한다.</FIELD2>
      <DESC>복수 명사 뒤 동사 원형</DESC>
    </CONTENT>
    <CONTENT No="008" Type="" Group="1">
      <FIELD1 Name="e_008">John's house is on the hill.</FIELD1>
      <FIELD2 Name="k_008">존의 집은 언덕위에 있다.</FIELD2>
      <DESC>on the hill은 장소를 나타내는 전+명구 부사</DESC>
    </CONTENT>
    <CONTENT No="010" Type="" Group="1">
      <FIELD1 Name="e_010">Here is what you ordered.</FIELD1>
      <FIELD2 Name="k_010">당신이 주문한 것이 여기 있어요.</FIELD2>
      <DESC>주어는 what you ordered 명사절, here는 부사,도치</DESC>
    </CONTENT>
    <CONTENT No="012" Type="" Group="1">
      <FIELD1 Name="e_012">The water in the pot is boiling.</FIELD1>
      <FIELD2 Name="k_012">냄비 안에 물은 끓는다.</FIELD2>
      <DESC>in the pot 은 전+명구로 형용사구.</DESC>
    </CONTENT>
    <CONTENT No="015" Type="" Group="1">
      <FIELD1 Name="e_015">John's plan is to take Michelle to Egypt as soon as possible.</FIELD1>
      <FIELD2 Name="k_015">존의 계획은 가능한한 빨리 이집트로 미셀을 데려 가는 것이다.</FIELD2>
      <DESC>to take 는 준동사. 준동사가 나오면 (1) 자/타, (2) 부사 여부 확인</DESC>
    </CONTENT>
    <CONTENT No="016" Type="" Group="1">
      <FIELD1 Name="e_016">The only thing you have to remember is to do your best in every situation.</FIELD1>
      <FIELD2 Name="k_016">네가 기억해야 할 단 한가지 것은 모든 상황에서 너의 최선을 다하는 것이다.</FIELD2>
      <DESC>you have to ~ 는 thing 을 수식하는 관계대명사절.</DESC>
    </CONTENT>
    <CONTENT No="017" Type="" Group="1">
      <FIELD1 Name="e_017">All you have to do is follow the instructions.</FIELD1>
      <FIELD2 Name="k_017">네가 해야 하는 모든 것은 지시를 따르는 것이다.</FIELD2>
      <DESC>you have to do 는 all 을 수식하는 절. 주어가 to do 와 같은 구를 포함하면 뒤 to생략</DESC>
    </CONTENT>
    <CONTENT No="019" Type="" Group="1">
      <FIELD1 Name="e_019">The main question at this time is whether John should go there or not.</FIELD1>
      <FIELD2 Name="k_019">이 시점에 주요 질문은 존이 그곳에 가야 하는지 아닌지 이다.</FIELD2>
      <DESC>main과 at tihis time은 question을 앞뒤로 수석. Whether는 조건의 명사절 이끔</DESC>
    </CONTENT>
    <CONTENT No="020" Type="" Group="1">
      <FIELD1 Name="e_020">That was what they needed in order to treat the monkey properly.</FIELD1>
      <FIELD2 Name="k_020">그것은 그들이 원숭이를 제대로 치료 하기 위해서 필요한 것이었다.</FIELD2>
      <DESC>What they needed ~ 보어로 명사절</DESC>
    </CONTENT>
    <CONTENT No="024" Type="" Group="1">
      <FIELD1 Name="e_024">I know when to stop.</FIELD1>
      <FIELD2 Name="k_024">나는 언제 정지 해야 하는지를 안다.</FIELD2>
      <DESC>when to stop 은 의문사 + 부정사로 명사구</DESC>
    </CONTENT>
    <CONTENT No="025" Type="" Group="1">
      <FIELD1 Name="e_025">I  know how to use this machine.</FIELD1>
      <FIELD2 Name="k_025">나는 이 기계를 어떻게 사용하는지를 안다.</FIELD2>
      <DESC>how to use 는 의문사 + 부정사. 명사구, 목적어</DESC>
    </CONTENT>
    <CONTENT No="026" Type="" Group="1">
      <FIELD1 Name="e_026">Richard doesn't know  when he has to go home.</FIELD1>
      <FIELD2 Name="k_026">리쳐드는 그가 언제 집으로 가야 하는지를 모른다.</FIELD2>
      <DESC>when he has to go, 명사적, 목적어</DESC>
    </CONTENT>
    <CONTENT No="027" Type="" Group="1">
      <FIELD1 Name="e_027">Richard said that he was very hungry.</FIELD1>
      <FIELD2 Name="k_027">리쳐드는 그가 매우 배고프다고 말 했다.</FIELD2>
      <DESC>that he was ~ , that절= 명사절 목적어, 시제일치</DESC>
    </CONTENT>
    <CONTENT No="028" Type="" Group="1">
      <FIELD1 Name="e_028">I wonder if Richard can get home by 5.</FIELD1>
      <FIELD2 Name="k_028">나는 리쳐드가 5 시 까지 집에 갈 수 있을 지 의문이다.</FIELD2>
      <DESC>if ~ 명사절=조건절, 목적어</DESC>
    </CONTENT>
    <CONTENT No="029" Type="" Group="1">
      <FIELD1 Name="e_029">Richard takes care of all his animals whenever possible.</FIELD1>
      <FIELD2 Name="k_029">리쳐드는 가능 할 때마다 그의 모든 동물들을 보살 핀다.</FIELD2>
      <DESC>takes care of 는 동사구. Whenever possible 은 whenever it is possible 에서 it is 가 생략</DESC>
    </CONTENT>
    <CONTENT No="030" Type="" Group="1">
      <FIELD1 Name="e_030">John bought a nice ring for Michelle on her birthday.</FIELD1>
      <FIELD2 Name="k_030">존은 그녀의 생일날에 미셀을 위해서 좋은 반지를 사주었다.</FIELD2>
      <DESC>for michelle 과 on her birthday 는 전명구</DESC>
    </CONTENT>
    <CONTENT No="031" Type="" Group="1">
      <FIELD1 Name="e_031">Michelle gave John a walnut.</FIELD1>
      <FIELD2 Name="k_031">미셀은 존에게 호도를 하나 주었다.</FIELD2>
      <DESC>4 형식. 간목은 단어인 명사와 인격체가 주로 온다.</DESC>
    </CONTENT>
    <CONTENT No="032" Type="" Group="1">
      <FIELD1 Name="e_032">I will tell them the true story if they ask me.</FIELD1>
      <FIELD2 Name="k_032">나는 그들이 나에게 묻는다면 그들에게 사실 이야기를 말 할 것이다.</FIELD2>
      <DESC>if they ask me 는 (조건)부사절.</DESC>
    </CONTENT>
    <CONTENT No="033" Type="" Group="1">
      <FIELD1 Name="e_033">Please show me your picture-ID.</FIELD1>
      <FIELD2 Name="k_033">나에게 당신의 사진증명서를 보여 주세요.</FIELD2>
      <DESC>동사 원형이 먼저 나오면 명령문.</DESC>
    </CONTENT>
    <CONTENT No="034" Type="" Group="1">
      <FIELD1 Name="e_034">John gave Michelle flowers which he got from the flower stand at the corner.</FIELD1>
      <FIELD2 Name="k_034">존은 미셀에게 그가 코너에 있는 꽃가게로 부터 산 꽃들을 주었습니다.</FIELD2>
      <DESC>flowers which he~ 선행사와 which가 이끄는 관계대명사 절</DESC>
    </CONTENT>
    <CONTENT No="035" Type="" Group="1">
      <FIELD1 Name="e_035">The doctor showed Richard how to send the test results to his office.</FIELD1>
      <FIELD2 Name="k_035">의사는 리차드에게 그의 사무실로 시험 결과를 어떻게 보내는지를 보여 주었습니다.</FIELD2>
      <DESC>how to ~ 는 의문사 + 부정사로 목적어와 부사 취함.</DESC>
    </CONTENT>
    <CONTENT No="036" Type="" Group="1">
      <FIELD1 Name="e_036">Michelle informed John when to call her.</FIELD1>
      <FIELD2 Name="k_036">미셀은 존에게 그녀에게 언제 전화 걸지를 알려 주었습니다.</FIELD2>
      <DESC>when to call her 도 의문사 + 부정사.</DESC>
    </CONTENT>
    <CONTENT No="037" Type="" Group="1">
      <FIELD1 Name="e_037">Michelle told me how happy she was.</FIELD1>
      <FIELD2 Name="k_037">미셀은 나에게 그녀가 얼마나 행복한지를 말했습니다.</FIELD2>
      <DESC>how happy she was 는 감탄문또는 의문사 절로도 볼 수 있음</DESC>
    </CONTENT>
    <CONTENT No="038" Type="" Group="1">
      <FIELD1 Name="e_038">John taught Michelle how to use the e-mail system.</FIELD1>
      <FIELD2 Name="k_038">존은 미셀에게 이 메일 시스템을 어떻게 사용하는지를 가르쳐 주었습니다.</FIELD2>
      <DESC>how to ~ 의문사 + 부정사.</DESC>
    </CONTENT>
    <CONTENT No="039" Type="" Group="1">
      <FIELD1 Name="e_039">John told Michelle where he was going to stay in Egypt.</FIELD1>
      <FIELD2 Name="k_039">존은 미셀에게 그가 이집트에서 어디에 머물지를 말 했습니다.</FIELD2>
      <DESC>where he was ~ 는 의문사절로 목적절. 직접 목적어로 의문사절이 옴.</DESC>
    </CONTENT>
    <CONTENT No="040" Type="" Group="1">
      <FIELD1 Name="e_040">Richard told John that he didn't know what he was supposed to do when the monkey was sick.</FIELD1>
      <FIELD2 Name="k_040">리쳐드는 존에게 그는 원숭이가 아플때 그가 무엇을 해야만 하는지를 모른다고 말 했습니다.</FIELD2>
      <DESC>what he was supposed to ~는 know 의 목적절로 의문대명사절임. 미래의 의무를 나타내는 동사구</DESC>
    </CONTENT>
    <CONTENT No="041" Type="" Group="1">
      <FIELD1 Name="e_041">Richard assured the doctor that it would not happen again.</FIELD1>
      <FIELD2 Name="k_041">리쳐드는 의사에게 그것이 다시는 일어 나지 않을 것을 확신 시켰습니다.</FIELD2>
      <DESC>that it ~ 절은 명사절으로 직접 목적어로 사용.</DESC>
    </CONTENT>
    <CONTENT No="042" Type="" Group="1">
      <FIELD1 Name="e_042">John never lets his parents down.</FIELD1>
      <FIELD2 Name="k_042">존은 절대로 그의 부모님을 실망 시키지 않습니다.</FIELD2>
      <DESC>let 사역동사 동사는 원형 부정사, Down 부사, 목적 보어</DESC>
    </CONTENT>
    <CONTENT No="043" Type="" Group="1">
      <FIELD1 Name="e_043">They call me Sam.</FIELD1>
      <FIELD2 Name="k_043">그들은 나를 샘이라고 부릅니다.</FIELD2>
      <DESC>5 형식 동사. 목적어의 성명을 지칭.</DESC>
    </CONTENT>
    <CONTENT No="044" Type="" Group="1">
      <FIELD1 Name="e_044">John saw the monkey running.</FIELD1>
      <FIELD2 Name="k_044">존은 원숭이가 뛰는 것을 보았습니다.</FIELD2>
      <DESC>saw 는 지각동사, 목적어의 상태가 running</DESC>
    </CONTENT>
    <CONTENT No="045" Type="" Group="1">
      <FIELD1 Name="e_045">Richard found the monkey crying at the corner of the cage.</FIELD1>
      <FIELD2 Name="k_045">리쳐드는 원승이가 철장 우리 구석에서 울고 있는 것을 발견 했습니다.</FIELD2>
      <DESC>crying 은 현재 분사로 목적 보어로 사용 됨</DESC>
    </CONTENT>
    <CONTENT No="046" Type="" Group="1">
      <FIELD1 Name="e_046">The doctor wanted Richard to visit his office this afternoon.</FIELD1>
      <FIELD2 Name="k_046">의사는 리처드가 이 오후에 그의 사무실을 방문 할 것을 원했습니다.</FIELD2>
      <DESC>want는 to 부정사를 데려옴</DESC>
    </CONTENT>
    <CONTENT No="047" Type="" Group="1">
      <FIELD1 Name="e_047">John asked Richard to wait one more day before he put the monkey somewhere else.</FIELD1>
      <FIELD2 Name="k_047">존은 리쳐드에게 그가 그 밖에 다른 곳으로 원숭이를 넣기 전에 하루를 더 기다려 줄 것을 요청했습니다.</FIELD2>
      <DESC>before ~ 시간 부사절, ~ 하기전에</DESC>
    </CONTENT>
    <CONTENT No="048" Type="" Group="1">
      <FIELD1 Name="e_048">Michelle thinks it difficult to stay in Egypt for 5 years.</FIELD1>
      <FIELD2 Name="k_048">미셀은 5 년 동안 이집트에 머문다는 것이 어렵다고 생각 합니다.</FIELD2>
      <DESC>it 는 그 뒤에 나오는 to stay ~ 라는 부정사구를 대신 하는 가 목적어. To ~ 이하가 진목적어.</DESC>
    </CONTENT>
    <CONTENT No="049" Type="" Group="1">
      <FIELD1 Name="e_049">They kept it a secret that the monkey had a virus which can kill people.</FIELD1>
      <FIELD2 Name="k_049">그들은 원숭이가 사람을 죽일 수 있는 바이러스를 가지고 있다는 것을 비밀로 했습니다.</FIELD2>
      <DESC>it은 that monkey~로 시작하는 명사절을 대신하는 가 목적어</DESC>
    </CONTENT>
    <CONTENT No="050" Type="" Group="1">
      <FIELD1 Name="e_050">John made it clear that he disagreed to what the doctor proposed.</FIELD1>
      <FIELD2 Name="k_050">존은 그가 의사가 제안한 것에 동의 하지 않는 다는 것을 분명히 했습니다.</FIELD2>
      <DESC>it 는 가목적어 that 이하가 명사절로 진목적어</DESC>
    </CONTENT>
    <CONTENT No="051" Type="" Group="1">
      <FIELD1 Name="e_051">I often heard it said that practice makes perfect.</FIELD1>
      <FIELD2 Name="k_051">나는 연습이 완전을 만든다는 것이 말해 지는 것을 자주 듣습니다.</FIELD2>
      <DESC>often 은 빈도 부사. 일반 동사 앞에. It 는 가목적어 that 이하는 진목적어.</DESC>
    </CONTENT>
    <CONTENT No="B00" Type="" Group="8">
      <FIELD1 Name="e_B00">Once you see all those animals you should feel better.</FIELD1>
      <FIELD2 Name="k_B00">네가 일단 저 동물들을 보면 너의 기분이 더 좋아 질 거야.</FIELD2>
      <DESC>Once ~ 절, ~ 하기만 하면,    should  조동사 추측 (거의) 할것이다 확신</DESC>
    </CONTENT>
    <CONTENT No="B01" Type="" Group="8">
      <FIELD1 Name="e_B01">I need to fix my car as soon as possible.</FIELD1>
      <FIELD2 Name="k_B01">나는 가능한 한 빨리 내 차를 고치는 것이 필요하다.</FIELD2>
      <DESC>as soon as possible. 가능한 빨리(관용구)
S. need to~ ~할 필요가 있다.  to 부정사구</DESC>
    </CONTENT>
    <CONTENT No="B08" Type="" Group="8">
      <FIELD1 Name="e_B08">Who is that? To tell you the truth, I don't like him that much.</FIELD1>
      <FIELD2 Name="k_B08">저 사람은 누구입니까? 솔직히 말하자면, 나는 그다지 그를 좋아 하지 않습니다.</FIELD2>
      <DESC>To tell you the truth  너에게 사실을 말하자면(솔직히 말하자면) 관용구</DESC>
    </CONTENT>
    <CONTENT No="B09" Type="" Group="8">
      <FIELD1 Name="e_B09">One should keep one's promise; otherwise no one will trust him or her.</FIELD1>
      <FIELD2 Name="k_B09">사람은 약속을 지켜야 해요. 그렇지 않으면 아무도 그 사람을 믿지 않을 겁니다.</FIELD2>
      <DESC>성별을 특정할 수 없어, 중성적인 표현을 쓰는 대신 him or her 를 썼다. 아마도 앞에 no one이 있어서, 다시  someone이나 somebody를 쓰기에는 반복이 되어서 그럴듯</DESC>
    </CONTENT>
    <CONTENT No="B10" Type="" Group="8">
      <FIELD1 Name="e_B10">Speaking of the tennis match, this is John's last one of the season.</FIELD1>
      <FIELD2 Name="k_B10">테니스 경기로 말하자면, 이것은 그 시즌 존의 마지막 경기 입니다.</FIELD2>
      <DESC>Speaking of ~ , ~으로 말하자면, last one 의  one은 앞의 tennis match를 대신 하는 대명사 역할</DESC>
    </CONTENT>
    <CONTENT No="B12" Type="" Group="8">
      <FIELD1 Name="e_B12">I feel sick to my stomach.</FIELD1>
      <FIELD2 Name="k_B12">내 위장에 아픔을 느낀다.</FIELD2>
      <DESC>sick 이  I  의 상태이므로 보어.</DESC>
    </CONTENT>
    <CONTENT No="B13" Type="" Group="8">
      <FIELD1 Name="e_B13">Feel free to call me whenever you want to play tennis.</FIELD1>
      <FIELD2 Name="k_B13">당신이 테니스 경기를 하고 싶을 때 는 언제든지 사양하지 말고  나에게 전화를 하세요.</FIELD2>
      <DESC>Feel free to ~ , 편하게 ~ 하세요. 
whenever ~, ~할때마다</DESC>
    </CONTENT>
    <CONTENT No="B14" Type="" Group="8">
      <FIELD1 Name="e_B14">I have two sisters, and both of them are sick. To make matters worse, they have to take their final exams this week.</FIELD1>
      <FIELD2 Name="k_B14">나는 누나가 2 명 있는데 모두 아파요. 설상가상으로 그들은 이번 주에 학기말 시험을 쳐야 해요.</FIELD2>
      <DESC>To make matters worse  설상 가상으로</DESC>
    </CONTENT>
    <CONTENT No="B15" Type="" Group="8">
      <FIELD1 Name="e_B15">How come you are not wearing a yellow uniform today?</FIELD1>
      <FIELD2 Name="k_B15">너는 어째서 오늘 노란 유니폼을 입지 않고 있니?</FIELD2>
      <DESC>How come  why를 대체할 수 있는 의문문인데, 다른점은 뒤에 주어 동사가 도치되지 않는다</DESC>
    </CONTENT>
    <CONTENT No="B16" Type="" Group="8">
      <FIELD1 Name="e_B16">I have to make a decision by 10:30.</FIELD1>
      <FIELD2 Name="k_B16">나는 10 시 30 분까지 결정을 내려야 해요.</FIELD2>
      <DESC>decide 대신 주요 동사인 make + 명사로 같은 의미를 가짐. 동사구?</DESC>
    </CONTENT>
    <CONTENT No="B18" Type="" Group="8">
      <FIELD1 Name="e_B18">Do you mind if I give you some advice on that? It is a very important tip on how to use the court.</FIELD1>
      <FIELD2 Name="k_B18">너는 내가 그것에 대해서 어떤 조언을 한다면 꺼려 하시겠어요? 그것은 코트를 사용하는데 있어서 매우 중요한 정보가 될 것입니다.</FIELD2>
      <DESC>do you mind는 꺼리느냐는 말이므로 긍정의 대답일때는 No을 씀.
how to~  의문사구</DESC>
    </CONTENT>
    <CONTENT No="B18b" Type="" Group="8">
      <FIELD1 Name="e_B18b">No, not at all. It sounds like you know what you are talking about.</FIELD1>
      <FIELD2 Name="k_B18b">아니요, 전혀 상관 없습니다. 당신이 말하는 것에 대해 잘 아는 것 같군요.</FIELD2>
      <DESC>It sounds like ~ . ~하게 들린다(한 거 같다)</DESC>
    </CONTENT>
    <CONTENT No="B19" Type="" Group="8">
      <FIELD1 Name="e_B19">You are much better than me.</FIELD1>
      <FIELD2 Name="k_B19">당신은 나보다 훨씬 더 잘해요.</FIELD2>
      <DESC>much + 비교급 - 비교급 강조</DESC>
    </CONTENT>
    <CONTENT No="B19b" Type="" Group="8">
      <FIELD1 Name="e_B19b">No. Don't be modest. Everyone knows that you are the best player around here.</FIELD1>
      <FIELD2 Name="k_B19b">아니. 겸손해 하지 마. 모든 사람들은 당신이 이 주변에서 최고의 선수라는 것을 알고 있다.</FIELD2>
      <DESC>modest 겸손하다.</DESC>
    </CONTENT>
    <CONTENT No="B20" Type="" Group="8">
      <FIELD1 Name="e_B20">I can't believe that this is the last summer camp that I am attending with you guys.</FIELD1>
      <FIELD2 Name="k_B20">이것이 내가 너희들과 함께 참석하고 있는 마지막 여름 캠프라니 믿어 지지가 않는다.</FIELD2>
      <DESC>summer camp that~, ~ 하는 여름 캠프. 형용사 절. 선행사 + 관계대명사</DESC>
    </CONTENT>
    <CONTENT No="B21" Type="" Group="8">
      <FIELD1 Name="e_B21">There is some food on the table. Help yourself, but please don't feed the dog.We are trying to cut down the food cost.</FIELD1>
      <FIELD2 Name="k_B21">식탁 위에 음식이 좀 있어요. 마음껏 드시되 개에게는 먹이지 마세요. 음식 비용을 절감 하려고 노력 중입니다.</FIELD2>
      <DESC>cut down ~   줄이다, 절감하다</DESC>
    </CONTENT>
    <CONTENT No="B25" Type="" Group="8">
      <FIELD1 Name="e_B25">Would you bring more batteries for me?</FIELD1>
      <FIELD2 Name="k_B25">너는 나를 위해서 좀 더 많은 배터리를 가져다 줄래요?</FIELD2>
      <DESC>would, will 의 과거, 정중함을 표현하기 위해 사용.</DESC>
    </CONTENT>
    <CONTENT No="B26" Type="" Group="8">
      <FIELD1 Name="e_B26">May I ask you where I can find those batteries?</FIELD1>
      <FIELD2 Name="k_B26">내가 어디에서 그 배터리를 찿을 수 있을지 물어 봐도 되요?</FIELD2>
      <DESC>where = the place that 의 의미하는, 의문사절이면서 명사절</DESC>
    </CONTENT>
    <CONTENT No="B27" Type="" Group="8">
      <FIELD1 Name="e_B27">It goes without saying that I was so upset to see that.</FIELD1>
      <FIELD2 Name="k_B27">내가 그것을 보게 되어 매우 화가 났다는 것은 말할 것도 없다.</FIELD2>
      <DESC>It goes without saying that ~, ~  한 것은 말할것도 없다. 설명할 핊요 없이 당연한 것.</DESC>
    </CONTENT>
    <CONTENT No="B28" Type="" Group="8">
      <FIELD1 Name="e_B28">I had a hard time controlling the boat.</FIELD1>
      <FIELD2 Name="k_B28">나는 그 배를 조정하는데 어려운 시간을 가졌어요.</FIELD2>
      <DESC>
      </DESC>
    </CONTENT>
    <CONTENT No="B29" Type="" Group="8">
      <FIELD1 Name="e_B29">Please forgive me this time and I will make sure it won't happen again.</FIELD1>
      <FIELD2 Name="k_B29">이번에 나를 용서 해 주세요. 나는 이것이 다시 일어 나지 않도록 확실하게 할 것입니다.</FIELD2>
      <DESC>forgive me this time.  한번 만 용서해 주세요의 느낌.
make sure~   확실히 하겠다
will not = won't. will  의지의 표현</DESC>
    </CONTENT>
    <CONTENT No="B30" Type="" Group="8">
      <FIELD1 Name="e_B30">I would do anything for a cold drink.</FIELD1>
      <FIELD2 Name="k_B30">나는 찬 음료수를 위해서라면 무엇이든지 하려고 할 것입니다.</FIELD2>
      <DESC>would  과거형을 씀으로서, 실제로 하지 않을 수 있다는 것을 내포. 가정법 과거와 비슷한 원리</DESC>
    </CONTENT>
    <CONTENT No="B34" Type="" Group="8">
      <FIELD1 Name="e_B34">How much did you pay for that?</FIELD1>
      <FIELD2 Name="k_B34">그것을 위해서 얼마를 지불 했니?</FIELD2>
      <DESC>4번 문장 설명 참조</DESC>
    </CONTENT>
    <CONTENT No="B35" Type="" Group="8">
      <FIELD1 Name="e_B35">How do you open this door?</FIELD1>
      <FIELD2 Name="k_B35">너는 이 문을 어떻게 여니?</FIELD2>
      <DESC>
      </DESC>
    </CONTENT>
    <CONTENT No="B36" Type="" Group="8">
      <FIELD1 Name="e_B36">I hate this. This kind of thing makes me really angry.</FIELD1>
      <FIELD2 Name="k_B36">나는 이런 게 진짜 싫어. 이런 일은 나를 정말 화나게 한다.</FIELD2>
      <DESC>
      </DESC>
    </CONTENT>
    <CONTENT No="B36b" Type="" Group="8">
      <FIELD1 Name="e_B36b">Who wouldn't be? I don't blame you at all. I guess the next best thing is to get a refund from the company.</FIELD1>
      <FIELD2 Name="k_B36b">누가 안 그럴까요? 나는 너를 전혀 비난하지 않는다. 그 다음으로 좋은 것은 회사로부터 환불받는 것이라고 생각한다.</FIELD2>
      <DESC>
      </DESC>
    </CONTENT>
    <CONTENT No="B37" Type="" Group="8">
      <FIELD1 Name="e_B37">We are very sorry for all the trouble we’ve caused you, but that’s the way it is around here. Take it or leave it.</FIELD1>
      <FIELD2 Name="k_B37">우리가 원인이 된 모든 문제에 대해서 죄송 합니다만 이곳은 원래 이렇습니다. 받아드리던지 말던지 하세요.</FIELD2>
      <DESC>take it or leave it.
협상의 고수, 아쉬울게 없는 것 처럼 할때, 사던 말던 알아서 하세요.</DESC>
    </CONTENT>
    <CONTENT No="B38" Type="" Group="8">
      <FIELD1 Name="e_B38">How long will it take to fix it?</FIELD1>
      <FIELD2 Name="k_B38">그것을 고치는데 얼마나 걸릴까요?</FIELD2>
      <DESC>얼마나 걸릴지, 미래형을 사용해 봄</DESC>
    </CONTENT>
    <CONTENT No="B39" Type="" Group="8">
      <FIELD1 Name="e_B39">What a mess! What happened here?</FIELD1>
      <FIELD2 Name="k_B39">와, 엉망이네. 여기에 무슨일이 일어났나요?</FIELD2>
      <DESC>무엇이 일어났나.  what 이 주어, happen이 동사</DESC>
    </CONTENT>
    <CONTENT No="B39b" Type="" Group="8">
      <FIELD1 Name="e_B39b">Well, it looks like the problem went from bad to worse. I don't know what to say.</FIELD1>
      <FIELD2 Name="k_B39b">음, 문제가 점점 더 나빠진 것 같아요. 무슨 말을 해야 할지 모르겠어요.</FIELD2>
      <DESC>
      </DESC>
    </CONTENT>
    <CONTENT No="B40" Type="" Group="8">
      <FIELD1 Name="e_B40">John promised to visit Paul's office before he leaves for Egypt.</FIELD1>
      <FIELD2 Name="k_B40">존은 그가 이집트로 떠나기 전에 폴의 사무실을 방문 할 것을 약속했습니다.</FIELD2>
      <DESC>promise to ~</DESC>
    </CONTENT>
    <CONTENT No="B41" Type="" Group="8">
      <FIELD1 Name="e_B41">Let me know when she comes in.</FIELD1>
      <FIELD2 Name="k_B41">그녀가 들어오면 나에게 알려 주세요.</FIELD2>
      <DESC>let me know ~, ~ 를 알려주세요. inform me  의 의미</DESC>
    </CONTENT>
    <CONTENT No="B42" Type="" Group="8">
      <FIELD1 Name="e_B42">Why don't you give her a call and remind her that I will stop by around 9.</FIELD1>
      <FIELD2 Name="k_B42">너는 그녀에게 전화해서 그녀에게 내가 9 시경에 잠시 들릴 것이라는 것을 상기 시켜 주시지 그래요?</FIELD2>
      <DESC>why don't you ~, ~하는게 어때요.
give one a call. one 에게 전화를 하다. 동사구?
remind sb sth ~  sb 에게 sth 를 상기시키다.</DESC>
    </CONTENT>
    <CONTENT No="B43" Type="" Group="8">
      <FIELD1 Name="e_B43">I wonder if this pearl necklace will make her happy.</FIELD1>
      <FIELD2 Name="k_B43">나는 이 진주 목걸이가 그녀를 행복하게 만들어 줄지 아닐지를 의아하게 생각 한다.</FIELD2>
      <DESC>I wonder ~ , ~일지 궁금하다 또는 의아하다. 그럴지 않그럴지 모르겠다</DESC>
    </CONTENT>
    <CONTENT No="B45" Type="" Group="8">
      <FIELD1 Name="e_B45">Do you want me to verify that for you?</FIELD1>
      <FIELD2 Name="k_B45">너는 내가 당신을 위해서 그것을 확인해 주는 것을 원합니까?</FIELD2>
      <DESC>want sb to ~. sb가 ~ 하길 원하다.
verify 확인시키다. clarify 확실히하다</DESC>
    </CONTENT>
    <CONTENT No="B47" Type="" Group="8">
      <FIELD1 Name="e_B47">It was obvious that he failed the examination twice before he became a broadcaster.</FIELD1>
      <FIELD2 Name="k_B47">그가 방송인이 되기 전에 그 시험에 두 번 떨어졌다는 것이 확실해요.</FIELD2>
      <DESC>It is obvious (certain) ~. ~ 이 확실하다.
사람들이 말하는것에 의하면 확실하다고 본다.
I am sure ~. ~이 확실하다. (내가 확실하다고 믿는다)</DESC>
    </CONTENT>
    <CONTENT No="B48" Type="" Group="8">
      <FIELD1 Name="e_B48">The reason why he failed the exam was that he simply didn’t study hard enough.</FIELD1>
      <FIELD2 Name="k_B48">그가 시험에 떨어진 이유는 그가 단지 충분하게 열심히 공부 하지 않았기 때문이지요.</FIELD2>
      <DESC>The reason why  는 why나 reason만 으로 대체될 수도 있고, why~이후가 형용사절로 쓰임</DESC>
    </CONTENT>
    <CONTENT No="B50" Type="" Group="9">
      <FIELD1 Name="e_B50">They have been married for 50 years. John's grandpa used to be a lawyer, but he retired last year.</FIELD1>
      <FIELD2 Name="k_B50">그들은 결혼한지 50 년 째에요. 존의 할아버지는 전에 변호사 였지만 지난해 은퇴 했지요.</FIELD2>
      <DESC>have+p.p. for . ~ 동안 ~해왔다.
used to be~ ~이곤했다.</DESC>
    </CONTENT>
    <CONTENT No="B51" Type="" Group="9">
      <FIELD1 Name="e_B51">I hate to admit it, but it's true. I am a vegetarian.</FIELD1>
      <FIELD2 Name="k_B51">나는 그것을 인정하기 싫지만 그것은 사실입니다. 나는 채식 주의자 입니다.</FIELD2>
      <DESC>hate to admit ~, but , ~를 인정하기 싫지만 ..</DESC>
    </CONTENT>
    <CONTENT No="B52" Type="" Group="9">
      <FIELD1 Name="e_B52">Be sure to call me as soon as you get to Tokyo, will you?</FIELD1>
      <FIELD2 Name="k_B52">네가 토쿄에 도착하자 마자 나에게 전화하는 것을 확실하게 해주세요. 그래 주실래요?</FIELD2>
      <DESC>be sure to ~ . ~을 확실히 해주세요.</DESC>
    </CONTENT>
    <CONTENT No="B53" Type="" Group="9">
      <FIELD1 Name="e_B53">It's not easy for me to learn English and Japanese at the same time.</FIELD1>
      <FIELD2 Name="k_B53">내가 영어와 일본어를 동시에 배우는 것이 쉽지가 않네요.</FIELD2>
      <DESC>It 가주어 to ~ 진주어. for ~ . 의미상 주어</DESC>
    </CONTENT>
    <CONTENT No="B57" Type="" Group="9">
      <FIELD1 Name="e_B57">Will you have him deliver it to my office?</FIELD1>
      <FIELD2 Name="k_B57">당신은 그를 시켜서 이것을 나의 사무실로 배달하게 해 주실래요?</FIELD2>
      <DESC>have sb 동사원형 - 사역동사(make, let)</DESC>
    </CONTENT>
    <CONTENT No="B57b" Type="" Group="9">
      <FIELD1 Name="e_B57b">Certainly. That can be arranged. Where is your office?</FIELD1>
      <FIELD2 Name="k_B57b">확실히. 그것은 준비될 수 있어요. 당신의 사무실은 어디에 있습니까?</FIELD2>
      <DESC>
      </DESC>
    </CONTENT>
    <CONTENT No="B59" Type="" Group="9">
      <FIELD1 Name="e_B59">Having done that, I think I can go home now. . Is there anything else I have to do before I hit the road?</FIELD1>
      <FIELD2 Name="k_B59">그것을 마쳤으니 이제 지금 나는 집에 갈 수 있을거 같아요. 출발하기 전에 해야할 다른 일이 있을까요?</FIELD2>
      <DESC>현재 분사 ~ing p.p. ~하였으니,  현재분사의 해석은 다음 문장의 내용에 따라 해석, because, when, as 등다양하게 부사절로 바꿀 수 있음</DESC>
    </CONTENT>
    <CONTENT No="B59b" Type="" Group="9">
      <FIELD1 Name="e_B59b">Well, I can't think of anything. That must be it.</FIELD1>
      <FIELD2 Name="k_B59b">글쎄, 생각나는게 없네요. 그게 다일 거예요.</FIELD2>
      <DESC>
      </DESC>
    </CONTENT>
    <CONTENT No="B63" Type="" Group="9">
      <FIELD1 Name="e_B63">No one is worse than my ex-boyfriend.</FIELD1>
      <FIELD2 Name="k_B63">아무도 나의 전 남자 친구 보다 나쁜 사람은 없어요.</FIELD2>
      <DESC>부정 비교</DESC>
    </CONTENT>
    <CONTENT No="B64" Type="" Group="9">
      <FIELD1 Name="e_B64">Do you know what happened to him? How did he wind up like this?</FIELD1>
      <FIELD2 Name="k_B64">그에게 무슨 일이 일어났는지 아세요? 어쩌다 이렇게 됐을까?</FIELD2>
      <DESC>
      </DESC>
    </CONTENT>
    <CONTENT No="B64a" Type="" Group="9">
      <FIELD1 Name="e_B64a">I guess he must have fallen from the roof.</FIELD1>
      <FIELD2 Name="k_B64a">나는 그가 지붕에서 떨어졌음에 틀림없다고 생각해요.</FIELD2>
      <DESC>must have P.P 과거의 확실한 추측</DESC>
    </CONTENT>
    <CONTENT No="B67" Type="" Group="9">
      <FIELD1 Name="e_B67">You mean you didn't have the interview today?</FIELD1>
      <FIELD2 Name="k_B67">오늘 면접 안 봤다는 거야?</FIELD2>
      <DESC>You mean ~. 너가 한 말이 ~을 의미하는지 확인</DESC>
    </CONTENT>
    <CONTENT No="B68" Type="" Group="9">
      <FIELD1 Name="e_B68">Actually, I am not feeling well and I'd rather stay home tonight.</FIELD1>
      <FIELD2 Name="k_B68">사실은 나는 기분이 좋지 않고 그래서 오늘 밤 집에 있는 것이 낫겠어.</FIELD2>
      <DESC>would rather v. ~하는 편이 낫다(취향) than하고도 같이 잘 쓰임</DESC>
    </CONTENT>
    <CONTENT No="B69" Type="" Group="9">
      <FIELD1 Name="e_B69">I don't blame you. Well then, who can be sent to pick up the package?</FIELD1>
      <FIELD2 Name="k_B69">저는 당신을 비난하지 않습니다. 그럼, 누가 소포를 가지러 갈 수 있나요?</FIELD2>
      <DESC>
      </DESC>
    </CONTENT>
    <CONTENT No="B70" Type="" Group="9">
      <FIELD1 Name="e_B70">It seems to me he doesn't care about anything anymore.</FIELD1>
      <FIELD2 Name="k_B70">내가 보기에는 그는 더 이상 어떤 것에도 신경을 쓰지 않는 것 처럼 보여.</FIELD2>
      <DESC>It seems to me, 내가 보기엔</DESC>
    </CONTENT>
    <CONTENT No="B71" Type="" Group="9">
      <FIELD1 Name="e_B71">What do you think of the security guard who is sleeping while he's on duty?</FIELD1>
      <FIELD2 Name="k_B71">너는 근무시간에 잠을 자는 청원 경찰에 대해서 어떻게 생각 해요?</FIELD2>
      <DESC>What do you thinkg of ~ . ~에 대해 어떻게 생각하는지</DESC>
    </CONTENT>
    <CONTENT No="B73" Type="" Group="9">
      <FIELD1 Name="e_B73">That's why he is still around here even though he keeps messing up like this.</FIELD1>
      <FIELD2 Name="k_B73">그래서 계속 이렇게 엉망진창으로 만들어 놓고도 계속 여기 있는 거야.</FIELD2>
      <DESC>That's why~.  그것이 ~그러한 이유이다.
keeps messing up. 엉망으로 하다. mess = ruin, wreck</DESC>
    </CONTENT>
    <CONTENT No="B74" Type="" Group="9">
      <FIELD1 Name="e_B74">Do you know the reason why he did that? You wouldn't believe this but he said,＂There was nothing to do.＂</FIELD1>
      <FIELD2 Name="k_B74">너는 그가 왜 그것을 한 이유를 아니? 네가 그것을 믿으려 하지 않겠지만 그는 ＂할일이 없었다＂고 했어요.</FIELD2>
      <DESC>You wouldn't believe (너는 믿지 않으려고 하겠지만...)</DESC>
    </CONTENT>
    <CONTENT No="B75b" Type="" Group="9">
      <FIELD1 Name="e_B75b">Later, they found out that his father was the police chief. What a ridiculous story!</FIELD1>
      <FIELD2 Name="k_B75b">나중에, 그들은 그의 아버지가 경찰서장이었다는 것을 알게 되었다. 정말 말도 안 되는 이야기군요!</FIELD2>
      <DESC>
      </DESC>
    </CONTENT>
    <CONTENT No="B76" Type="" Group="9">
      <FIELD1 Name="e_B76">No wonder he didn't want to give his name.</FIELD1>
      <FIELD2 Name="k_B76">그가 그의 이름을 밝히는 것을 원하지 않는 것은 당연하지요.</FIELD2>
      <DESC>No wonder (that) ~ . ~하는게 놀랍지 않다(당연하다)</DESC>
    </CONTENT>
    <CONTENT No="B78" Type="" Group="9">
      <FIELD1 Name="e_B78">You know what? I haven't met a man as indecisive as you before.</FIELD1>
      <FIELD2 Name="k_B78">당신은 그것을 알아요? 나는 전에 당신과 같이 우유 부단한 사람을 만난 적이 없어요.</FIELD2>
      <DESC>You know what? 너그거 아니?
be supposed to ~ . ~ 하기로 되어 있다. (의무의 느낌)</DESC>
    </CONTENT>
    <CONTENT No="B78a" Type="" Group="9">
      <FIELD1 Name="e_B78a">Aren't you the person who is supposed to make decisions around here?</FIELD1>
      <FIELD2 Name="k_B78a">당신은 여기서 결정을 내려야 할 사람이 아닌가요?</FIELD2>
      <DESC>
      </DESC>
    </CONTENT>
    <CONTENT No="B79" Type="" Group="9">
      <FIELD1 Name="e_B79">Sorry. We are out of red tape. What if we use the yellow tape instead?</FIELD1>
      <FIELD2 Name="k_B79">미안해요. 우리는 빨간 테이프가 떨어 졌어요. 우리가 대신 노란 색 테이프를 사용한다면 어떨까요?</FIELD2>
      <DESC>out of ~ . ~가 떨어지다.
What if ~. ~은 어때?</DESC>
    </CONTENT>
    <CONTENT No="B80" Type="" Group="9">
      <FIELD1 Name="e_B80">She didn't realize what she was talking about until the teacher asked the question.</FIELD1>
      <FIELD2 Name="k_B80">그녀는 선생님이 질문을 하기 전까지 자신이 무슨 말을 하고 있는지 몰랐다.</FIELD2>
      <DESC>not realize ~ until ~. ~할 때 까지 ~을 깨닫지 못했다.</DESC>
    </CONTENT>
    <CONTENT No="B81" Type="" Group="9">
      <FIELD1 Name="e_B81">I don't know why you say that. What makes you say that?</FIELD1>
      <FIELD2 Name="k_B81">당신이 왜 그런 말을 하는지 모르겠어요. 무엇 때문에 그렇게 말하는건가요?</FIELD2>
      <DESC>What makes you~. 무엇이 널 그렇게 만드니? - 왜 그랬니</DESC>
    </CONTENT>
    <CONTENT No="B82" Type="" Group="9">
      <FIELD1 Name="e_B82">You look awfully tired and exhausted. I think you need a vacation. All you have to do is fill out this request form.</FIELD1>
      <FIELD2 Name="k_B82">너는 매우 피곤하고 지쳐 보여요. 나는 네가 휴가를 필요하다고 생각해요. 네가 해야 할 모든 것은 이 신청서 용지에 기입하는 것 뿐 입니다.</FIELD2>
      <DESC>All you have to do, fill out the request form</DESC>
    </CONTENT>
    <CONTENT No="B83" Type="" Group="9">
      <FIELD1 Name="e_B83">Don't get me wrong. Whatever you decide to do doesn't make any difference to me.</FIELD1>
      <FIELD2 Name="k_B83">나를 오해하지 마세요. 당신이 무엇을 하려고 결정하던지 나에게는 아무런 차이가 없어요.</FIELD2>
      <DESC>Don't get me wrong 나를 오해하지는 마세요.
doesn't make any difference 차이가 없다</DESC>
    </CONTENT>
    <CONTENT No="B83b" Type="" Group="9">
      <FIELD1 Name="e_B83b">Thanks for the suggestion, but I don't think I can afford it now.</FIELD1>
      <FIELD2 Name="k_B83b">제안은 고맙지만, 지금은 그럴 여유가 없을 것 같아요.</FIELD2>
      <DESC>
      </DESC>
    </CONTENT>
    <CONTENT No="B85" Type="" Group="9">
      <FIELD1 Name="e_B85">No matter how hard I study, I am not getting any better. I think I am in big trouble.</FIELD1>
      <FIELD2 Name="k_B85">내가 아무리 열심히 공부를 한다 해도 나는 조금도 나아지지 않아요. 나는 큰 문제 안에 있다고 생각해요.</FIELD2>
      <DESC>No matter how 부사.  아무리 ~하더라도</DESC>
    </CONTENT>
    <CONTENT No="B86" Type="" Group="9">
      <FIELD1 Name="e_B86">When it comes to studying, Peter's friend is much better than he is.</FIELD1>
      <FIELD2 Name="k_B86">공부에 관해서라면 피터의 친구가 그 보다 훨씬 낫지요.</FIELD2>
      <DESC>When it comes to ~ ing, ~에 관해서라면</DESC>
    </CONTENT>
    <CONTENT No="B89" Type="" Group="9">
      <FIELD1 Name="e_B89">While you may have a point there, I don't think there is anything to worry about.</FIELD1>
      <FIELD2 Name="k_B89">네가 거기에 요점을 가지고 있는 반면에, 나는 염려 할 어떤 것이 있다고 생각 하지 않아.</FIELD2>
      <DESC>While you may have a point there</DESC>
    </CONTENT>
    <CONTENT No="B90" Type="" Group="9">
      <FIELD1 Name="e_B90">In case you haven't heard this, John became one of the best managers in the company.</FIELD1>
      <FIELD2 Name="k_B90">네가 못들었을까봐 하는 말인데, 존은 회사에서 최고의 관리자 중 한 명이 되었다.</FIELD2>
      <DESC>In case ~. ~ 하는 경우에. ~를 대비하여 라는 의미로 잘 쓰인다.</DESC>
    </CONTENT>
    <CONTENT No="B91" Type="" Group="9">
      <FIELD1 Name="e_B91">Mr. Jung was so excited that he asked his personal assistant to buy everyone a drink. 
At that time, no one realized that it was a fatal mistake.</FIELD1>
      <FIELD2 Name="k_B91">정씨는 너무 들떠서 그는 모두 에게 한잔을 사라고 그의 개인 비서에게 요청 했어요. 
그 당시에는 아무도 그것이 치명적인 실수라고는 인식하지 못했어요.</FIELD2>
      <DESC>so ~ that ~ , 너무 ~해서 ~하다</DESC>
    </CONTENT>
    <CONTENT No="B92" Type="" Group="9">
      <FIELD1 Name="e_B92">Who are you looking for? 
You'd better realize that there is no way that you can find anyone around here without my help.</FIELD1>
      <FIELD2 Name="k_B92">누구를 찾고 있어요? 
당신은 나의 도움 없이는 여기서 누구도 찾을 수 없다는 것을 아는게 좋을 것입니다.</FIELD2>
      <DESC>you'd better realize ~, ~ 을 아는게 좋을 겁니다
had better의 약어(권고의 의미)</DESC>
    </CONTENT>
    <CONTENT No="B94" Type="" Group="9">
      <FIELD1 Name="e_B94">As far as I know, he died peacefully. I'd appreciate it if you would share this information with your friends.</FIELD1>
      <FIELD2 Name="k_B94">내가 아는 한, 그는 평화롭게 죽었다. 이 정보를 친구들과 공유해주시면 감사하겠습니다.</FIELD2>
      <DESC>as far as~ ~ 하는 한, I'd appreciate it</DESC>
    </CONTENT>
    <CONTENT No="B97" Type="" Group="9">
      <FIELD1 Name="e_B97">Mr. Abdullah said,＂The more I think about it, the more frustrated I get. Every year the government tells us how safe this river is, but I don't think they are telling us the truth.＂</FIELD1>
      <FIELD2 Name="k_B97">압둘라씨는＂내가 그것을 생각 하면 할수록 더 짜증이 나요. 매년 정부는 얼마나 이 강이 안전 한지를 말하지만 나는 그들이 우리에게 진실을 말하고 있다고 생각하지 않아요.＂라고 했습니다.</FIELD2>
      <DESC>The 형용사 비교 ~, The 형용사 비교 - 더~할 수록, 더 ~하게 되다.</DESC>
    </CONTENT>
    <CONTENT No="B98" Type="" Group="9">
      <FIELD1 Name="e_B98">From what I can see, it appears that they are not doing their job at all. Am I right?</FIELD1>
      <FIELD2 Name="k_B98">제가 보기에는 그들은 전혀 그들의 임무를 하지 않는 것처럼 보이는 군요. 제 말이 맞나요?</FIELD2>
      <DESC>From what I can see, it appears that~. 내가 보기엔 ~으로 보인다</DESC>
    </CONTENT>
    <CONTENT No="S001" Type="" Group="10">
      <FIELD1 Name="e_S001">Absolutely.</FIELD1>
      <FIELD2 Name="k_S001">당근이죠(물론이죠)</FIELD2>
      <DESC>Definetly</DESC>
    </CONTENT>
    <CONTENT No="S002" Type="" Group="10">
      <FIELD1 Name="e_S002">After you.</FIELD1>
      <FIELD2 Name="k_S002">먼저 가세요.</FIELD2>
      <DESC>
      </DESC>
    </CONTENT>
    <CONTENT No="S003" Type="" Group="10">
      <FIELD1 Name="e_S003">Are you in line?</FIELD1>
      <FIELD2 Name="k_S003">지금 줄에 서 계신거죠?</FIELD2>
      <DESC>
      </DESC>
    </CONTENT>
    <CONTENT No="S004" Type="" Group="10">
      <FIELD1 Name="e_S004">Are you kidding?</FIELD1>
      <FIELD2 Name="k_S004">놀리는거 아니죠?</FIELD2>
      <DESC>Are you teasing me?</DESC>
    </CONTENT>
    <CONTENT No="S005" Type="" Group="10">
      <FIELD1 Name="e_S005">Are you serious?</FIELD1>
      <FIELD2 Name="k_S005">그거 진짜예요?</FIELD2>
      <DESC>
      </DESC>
    </CONTENT>
    <CONTENT No="S006" Type="" Group="10">
      <FIELD1 Name="e_S006">At last.</FIELD1>
      <FIELD2 Name="k_S006">드디어</FIELD2>
      <DESC>Finally, Eventually</DESC>
    </CONTENT>
    <CONTENT No="S007" Type="" Group="10">
      <FIELD1 Name="e_S007">Be patient.</FIELD1>
      <FIELD2 Name="k_S007">조금만 참아 보세요</FIELD2>
      <DESC>
      </DESC>
    </CONTENT>
    <CONTENT No="S008" Type="" Group="10">
      <FIELD1 Name="e_S008">Be punctual!</FIELD1>
      <FIELD2 Name="k_S008">제시간에 좀 와!</FIELD2>
      <DESC>Be on time?</DESC>
    </CONTENT>
    <CONTENT No="S009" Type="" Group="10">
      <FIELD1 Name="e_S009">Better late than never.</FIELD1>
      <FIELD2 Name="k_S009">안하느니보단 늦는게 낫죠.</FIELD2>
      <DESC>
      </DESC>
    </CONTENT>
    <CONTENT No="S010" Type="" Group="10">
      <FIELD1 Name="e_S010">Better than nothing.</FIELD1>
      <FIELD2 Name="k_S010">없는 것 보다는 낫지요</FIELD2>
      <DESC>
      </DESC>
    </CONTENT>
    <CONTENT No="S011" Type="" Group="10">
      <FIELD1 Name="e_S011">Can't argue with that.</FIELD1>
      <FIELD2 Name="k_S011">그건 논란의 여지가 없죠</FIELD2>
      <DESC>There's no room for debate on that</DESC>
    </CONTENT>
    <CONTENT No="S012" Type="" Group="10">
      <FIELD1 Name="e_S012">Catch you later.</FIELD1>
      <FIELD2 Name="k_S012">나중에 보자구요</FIELD2>
      <DESC>See you later.</DESC>
    </CONTENT>
    <CONTENT No="S013" Type="" Group="10">
      <FIELD1 Name="e_S013">Check it out.</FIELD1>
      <FIELD2 Name="k_S013">확인해 보세요</FIELD2>
      <DESC>
      </DESC>
    </CONTENT>
    <CONTENT No="S014" Type="" Group="10">
      <FIELD1 Name="e_S014">Could be.</FIELD1>
      <FIELD2 Name="k_S014">그럴 수도 있죠</FIELD2>
      <DESC>
      </DESC>
    </CONTENT>
    <CONTENT No="S015" Type="" Group="10">
      <FIELD1 Name="e_S015">Couldn't be better than this.</FIELD1>
      <FIELD2 Name="k_S015">이보다 더 좋을 순 없어</FIELD2>
      <DESC>
      </DESC>
    </CONTENT>
    <CONTENT No="S016" Type="" Group="10">
      <FIELD1 Name="e_S016">Didn't I make myself clear?</FIELD1>
      <FIELD2 Name="k_S016">제 입장을 확실하게 말하지 않았나요?</FIELD2>
      <DESC>
      </DESC>
    </CONTENT>
    <CONTENT No="S017" Type="" Group="10">
      <FIELD1 Name="e_S017">Do you follow me?</FIELD1>
      <FIELD2 Name="k_S017">제 말 알아 듣겠어요?</FIELD2>
      <DESC>Do you get it? or get it</DESC>
    </CONTENT>
    <CONTENT No="S018" Type="" Group="10">
      <FIELD1 Name="e_S018">Don’t miss the boat.</FIELD1>
      <FIELD2 Name="k_S018">기회를 놓지지 마세요</FIELD2>
      <DESC>chance or opportunity
(보트를 놓치듯이)</DESC>
    </CONTENT>
    <CONTENT No="S019" Type="" Group="10">
      <FIELD1 Name="e_S019">Don't be a chicken.</FIELD1>
      <FIELD2 Name="k_S019">너무 소심하게 굴지 말아요.</FIELD2>
      <DESC>Don't be so timid.</DESC>
    </CONTENT>
    <CONTENT No="S020" Type="" Group="10">
      <FIELD1 Name="e_S020">Don't be modest.</FIELD1>
      <FIELD2 Name="k_S020">겸손해 하지 말아요</FIELD2>
      <DESC>
      </DESC>
    </CONTENT>
    <CONTENT No="S021" Type="" Group="10">
      <FIELD1 Name="e_S021">Don't push me!</FIELD1>
      <FIELD2 Name="k_S021">너무 강요 하지 말아요</FIELD2>
      <DESC>too demanding</DESC>
    </CONTENT>
    <CONTENT No="S022" Type="" Group="10">
      <FIELD1 Name="e_S022">Easy does it.</FIELD1>
      <FIELD2 Name="k_S022">천천히 해요.</FIELD2>
      <DESC>Take your time.
 (+ 진정해요, 조심스럽게 해요)</DESC>
    </CONTENT>
    <CONTENT No="S023" Type="" Group="10">
      <FIELD1 Name="e_S023">Enough is enough.</FIELD1>
      <FIELD2 Name="k_S023">충분 하니까 이제 그만 해요</FIELD2>
      <DESC>
      </DESC>
    </CONTENT>
    <CONTENT No="S024" Type="" Group="10">
      <FIELD1 Name="e_S024">Far from it.</FIELD1>
      <FIELD2 Name="k_S024">아직 멀었지요</FIELD2>
      <DESC>
      </DESC>
    </CONTENT>
    <CONTENT No="S025" Type="" Group="10">
      <FIELD1 Name="e_S025">Fifty-fifty.</FIELD1>
      <FIELD2 Name="k_S025">50:50 이죠.</FIELD2>
      <DESC>
      </DESC>
    </CONTENT>
    <CONTENT No="S026" Type="" Group="10">
      <FIELD1 Name="e_S026">For what?</FIELD1>
      <FIELD2 Name="k_S026">왜? 뭣땀시?</FIELD2>
      <DESC>
      </DESC>
    </CONTENT>
    <CONTENT No="S027" Type="" Group="10">
      <FIELD1 Name="e_S027">Get lost!</FIELD1>
      <FIELD2 Name="k_S027">당장 꺼져 버려</FIELD2>
      <DESC>
      </DESC>
    </CONTENT>
    <CONTENT No="S028" Type="" Group="10">
      <FIELD1 Name="e_S028">Get real!</FIELD1>
      <FIELD2 Name="k_S028">현실적이 되세요. 냉정해 지세요</FIELD2>
      <DESC>
      </DESC>
    </CONTENT>
    <CONTENT No="S029" Type="" Group="10">
      <FIELD1 Name="e_S029">In your dreams!</FIELD1>
      <FIELD2 Name="k_S029">꿈깨</FIELD2>
      <DESC>Wake up and smell the coffee! (정신 차리고 현실을 받아들여라!)</DESC>
    </CONTENT>
    <CONTENT No="S030" Type="" Group="10">
      <FIELD1 Name="e_S030">Give it a try.</FIELD1>
      <FIELD2 Name="k_S030">한번 해 보세요.</FIELD2>
      <DESC>Give it a shot</DESC>
    </CONTENT>
    <CONTENT No="S031" Type="" Group="10">
      <FIELD1 Name="e_S031">Gladly.</FIELD1>
      <FIELD2 Name="k_S031">기꺼이</FIELD2>
      <DESC>With pleasure</DESC>
    </CONTENT>
    <CONTENT No="S032" Type="" Group="10">
      <FIELD1 Name="e_S032">Go for it.</FIELD1>
      <FIELD2 Name="k_S032">잘해봐! (화이팅! )</FIELD2>
      <DESC>
      </DESC>
    </CONTENT>
    <CONTENT No="S033" Type="" Group="10">
      <FIELD1 Name="e_S033">Good enough.</FIELD1>
      <FIELD2 Name="k_S033">그 정도면 충분히 좋아요.</FIELD2>
      <DESC>
      </DESC>
    </CONTENT>
    <CONTENT No="S034" Type="" Group="10">
      <FIELD1 Name="e_S034">Grow up!</FIELD1>
      <FIELD2 Name="k_S034">좀 철좀 들어라</FIELD2>
      <DESC>
      </DESC>
    </CONTENT>
    <CONTENT No="S035" Type="" Group="10">
      <FIELD1 Name="e_S035">Guess what?</FIELD1>
      <FIELD2 Name="k_S035">뭔지 알아 맞추어 봐요</FIELD2>
      <DESC>Take a guess. (Can you guess?)</DESC>
    </CONTENT>
    <CONTENT No="S036" Type="" Group="10">
      <FIELD1 Name="e_S036">Hang in there.</FIELD1>
      <FIELD2 Name="k_S036">잘 견디고 있어 주세요</FIELD2>
      <DESC>
      </DESC>
    </CONTENT>
    <CONTENT No="S037" Type="" Group="10">
      <FIELD1 Name="e_S037">He is history to me.</FIELD1>
      <FIELD2 Name="k_S037">그는 저에게 이미 지난 일</FIELD2>
      <DESC>
      </DESC>
    </CONTENT>
    <CONTENT No="S038" Type="" Group="10">
      <FIELD1 Name="e_S038">Hold on.</FIELD1>
      <FIELD2 Name="k_S038">잠깐 기다리세요</FIELD2>
      <DESC>wait, hang on</DESC>
    </CONTENT>
    <CONTENT No="S039" Type="" Group="10">
      <FIELD1 Name="e_S039">How many times do I have to say?</FIELD1>
      <FIELD2 Name="k_S039">몇번을 말해야 알겠어요?</FIELD2>
      <DESC>
      </DESC>
    </CONTENT>
    <CONTENT No="S040" Type="" Group="10">
      <FIELD1 Name="e_S040">I am (deeply) touched.</FIELD1>
      <FIELD2 Name="k_S040">정말 감동했어요 ㅠ.ㅠ</FIELD2>
      <DESC>moved</DESC>
    </CONTENT>
    <CONTENT No="S041" Type="" Group="10">
      <FIELD1 Name="e_S041">I am all set.</FIELD1>
      <FIELD2 Name="k_S041">준비 끝!</FIELD2>
      <DESC>I am done</DESC>
    </CONTENT>
    <CONTENT No="S042" Type="" Group="10">
      <FIELD1 Name="e_S042">I am aware of that.</FIELD1>
      <FIELD2 Name="k_S042">그점에 대해서는 잘 알고 있습니다.</FIELD2>
      <DESC>I knew it.</DESC>
    </CONTENT>
    <CONTENT No="S043" Type="" Group="10">
      <FIELD1 Name="e_S043">I am broke.</FIELD1>
      <FIELD2 Name="k_S043">저 무일푼입니다</FIELD2>
      <DESC>(완전 파산상태예요)</DESC>
    </CONTENT>
    <CONTENT No="S044" Type="" Group="10">
      <FIELD1 Name="e_S044">I am coming.</FIELD1>
      <FIELD2 Name="k_S044">지금 가요</FIELD2>
      <DESC>
      </DESC>
    </CONTENT>
    <CONTENT No="S045" Type="" Group="10">
      <FIELD1 Name="e_S045">I am crazy about her.</FIELD1>
      <FIELD2 Name="k_S045">나는 그녀에 빠졌어요</FIELD2>
      <DESC>
      </DESC>
    </CONTENT>
    <CONTENT No="S046" Type="" Group="10">
      <FIELD1 Name="e_S046">I am fed up with this.</FIELD1>
      <FIELD2 Name="k_S046">정말 진저리가 나요</FIELD2>
      <DESC>I am sick of it.</DESC>
    </CONTENT>
    <CONTENT No="S047" Type="" Group="10">
      <FIELD1 Name="e_S047">I am in need.</FIELD1>
      <FIELD2 Name="k_S047">궁색 합니다</FIELD2>
      <DESC>
      </DESC>
    </CONTENT>
    <CONTENT No="S048" Type="" Group="10">
      <FIELD1 Name="e_S048">I am on duty.</FIELD1>
      <FIELD2 Name="k_S048">근무중입니다</FIELD2>
      <DESC>
      </DESC>
    </CONTENT>
    <CONTENT No="S049" Type="" Group="10">
      <FIELD1 Name="e_S049">I am starving to death.</FIELD1>
      <FIELD2 Name="k_S049">배가 고파 죽겠네여</FIELD2>
      <DESC>
      </DESC>
    </CONTENT>
    <CONTENT No="S050" Type="" Group="10">
      <FIELD1 Name="e_S050">I am stuffed.</FIELD1>
      <FIELD2 Name="k_S050">배 불러요</FIELD2>
      <DESC>I am full.
 (더 이상 들어가지 못할 만큼 배부르다는 뜻으로도 쓰여요)</DESC>
    </CONTENT>
    <CONTENT No="S051" Type="" Group="10">
      <FIELD1 Name="e_S051">I can handle it.</FIELD1>
      <FIELD2 Name="k_S051">내가 할 수 있어요</FIELD2>
      <DESC>take care of</DESC>
    </CONTENT>
    <CONTENT No="S052" Type="" Group="10">
      <FIELD1 Name="e_S052">I can’t help it.</FIELD1>
      <FIELD2 Name="k_S052">어쩔수 없어요</FIELD2>
      <DESC>
      </DESC>
    </CONTENT>
    <CONTENT No="S053" Type="" Group="10">
      <FIELD1 Name="e_S053">I can't stand it.</FIELD1>
      <FIELD2 Name="k_S053">못 참겠어.</FIELD2>
      <DESC>견디기 힘들어</DESC>
    </CONTENT>
    <CONTENT No="S054" Type="" Group="10">
      <FIELD1 Name="e_S054">I feel the same way.</FIELD1>
      <FIELD2 Name="k_S054">저도 똑같이 느꼈어요.</FIELD2>
      <DESC>same here?</DESC>
    </CONTENT>
    <CONTENT No="S055" Type="" Group="10">
      <FIELD1 Name="e_S055">I got lost.</FIELD1>
      <FIELD2 Name="k_S055">난 길을 잃었어요</FIELD2>
      <DESC>
      </DESC>
    </CONTENT>
    <CONTENT No="S056" Type="" Group="10">
      <FIELD1 Name="e_S056">I have a long way to go.</FIELD1>
      <FIELD2 Name="k_S056">갈길이 머네요</FIELD2>
      <DESC>
      </DESC>
    </CONTENT>
    <CONTENT No="S057" Type="" Group="10">
      <FIELD1 Name="e_S057">I made it.</FIELD1>
      <FIELD2 Name="k_S057">제가 해냈어요!</FIELD2>
      <DESC>
      </DESC>
    </CONTENT>
    <CONTENT No="S058" Type="" Group="10">
      <FIELD1 Name="e_S058">I mean it.</FIELD1>
      <FIELD2 Name="k_S058">정말입니다. 농담아니에요.</FIELD2>
      <DESC>I am serious.</DESC>
    </CONTENT>
    <CONTENT No="S059" Type="" Group="10">
      <FIELD1 Name="e_S059">I owe you one .</FIELD1>
      <FIELD2 Name="k_S059">신세를 지네요</FIELD2>
      <DESC>
      </DESC>
    </CONTENT>
    <CONTENT No="S060" Type="" Group="10">
      <FIELD1 Name="e_S060">I taught myself.</FIELD1>
      <FIELD2 Name="k_S060">저 혼자 익혔어요</FIELD2>
      <DESC>(누가 가르쳐 준 사람 없이)</DESC>
    </CONTENT>
    <CONTENT No="S061" Type="" Group="10">
      <FIELD1 Name="e_S061">I will be in touch.</FIELD1>
      <FIELD2 Name="k_S061">제가 연락드릴께요.</FIELD2>
      <DESC>get in touch</DESC>
    </CONTENT>
    <CONTENT No="S062" Type="" Group="10">
      <FIELD1 Name="e_S062">Is that all?</FIELD1>
      <FIELD2 Name="k_S062">그게 전부에요?</FIELD2>
      <DESC>
      </DESC>
    </CONTENT>
    <CONTENT No="S063" Type="" Group="10">
      <FIELD1 Name="e_S063">It is humid.</FIELD1>
      <FIELD2 Name="k_S063">습하네요</FIELD2>
      <DESC>(습기가 많은 날씨)</DESC>
    </CONTENT>
    <CONTENT No="S064" Type="" Group="10">
      <FIELD1 Name="e_S064">It is muggy</FIELD1>
      <FIELD2 Name="k_S064">날이 후덥지근하네</FIELD2>
      <DESC>(온도 높고 습도 높고)</DESC>
    </CONTENT>
    <CONTENT No="S065" Type="" Group="10">
      <FIELD1 Name="e_S065">It is out of style.</FIELD1>
      <FIELD2 Name="k_S065">유행이 아니네요.</FIELD2>
      <DESC>
      </DESC>
    </CONTENT>
    <CONTENT No="S066" Type="" Group="10">
      <FIELD1 Name="e_S066">It makes sense.</FIELD1>
      <FIELD2 Name="k_S066">말 되네요</FIELD2>
      <DESC>
      </DESC>
    </CONTENT>
    <CONTENT No="S067" Type="" Group="10">
      <FIELD1 Name="e_S067">It’s not fair. (It's unfair)</FIELD1>
      <FIELD2 Name="k_S067">불공평해요</FIELD2>
      <DESC>
      </DESC>
    </CONTENT>
    <CONTENT No="S068" Type="" Group="10">
      <FIELD1 Name="e_S068">It's my turn.</FIELD1>
      <FIELD2 Name="k_S068">이번에 내 차례입니다</FIELD2>
      <DESC>
      </DESC>
    </CONTENT>
    <CONTENT No="S069" Type="" Group="10">
      <FIELD1 Name="e_S069">It's now or never.</FIELD1>
      <FIELD2 Name="k_S069">절호의 기회</FIELD2>
      <DESC>지금이 절호의 기회입니다. (지금이 아니면 절대)</DESC>
    </CONTENT>
    <CONTENT No="S070" Type="" Group="10">
      <FIELD1 Name="e_S070">It's on me. It's on the house.</FIELD1>
      <FIELD2 Name="k_S070">이건 제가 쏘는 겁니다 이것은 주인집에서 써비스!</FIELD2>
      <DESC>I will treat</DESC>
    </CONTENT>
    <CONTENT No="S071" Type="" Group="10">
      <FIELD1 Name="e_S071">Keep your chin up!</FIELD1>
      <FIELD2 Name="k_S071">기운을 내요</FIELD2>
      <DESC>(고개를 드세요. 낙담 하지 마세요 기운을 내요)</DESC>
    </CONTENT>
    <CONTENT No="S072" Type="" Group="10">
      <FIELD1 Name="e_S072">Let me see…</FIELD1>
      <FIELD2 Name="k_S072">어디 보자…</FIELD2>
      <DESC>(별 의미 없이 쓰는 접두어.. 음… 정도)</DESC>
    </CONTENT>
    <CONTENT No="S073" Type="" Group="10">
      <FIELD1 Name="e_S073">Let's give him a big hand.</FIELD1>
      <FIELD2 Name="k_S073">그에게 큰 박수를 보냅시다</FIELD2>
      <DESC>
      </DESC>
    </CONTENT>
    <CONTENT No="S074" Type="" Group="10">
      <FIELD1 Name="e_S074">Let's call it a day.</FIELD1>
      <FIELD2 Name="k_S074">오늘은 이걸로 마치죠</FIELD2>
      <DESC>wrap it up
(오늘은 여기까지 하죠)</DESC>
    </CONTENT>
    <CONTENT No="S075" Type="" Group="10">
      <FIELD1 Name="e_S075">Let's split the bill.</FIELD1>
      <FIELD2 Name="k_S075">나누어서 냅시다</FIELD2>
      <DESC>
      </DESC>
    </CONTENT>
    <CONTENT No="S076" Type="" Group="10">
      <FIELD1 Name="e_S076">Make yourself at home.</FIELD1>
      <FIELD2 Name="k_S076">내집인양 편하게 계세요</FIELD2>
      <DESC>Be my guest. 편한대로 하세요. 사양하지 마세요.</DESC>
    </CONTENT>
    <CONTENT No="S077" Type="" Group="10">
      <FIELD1 Name="e_S077">Money talks.</FIELD1>
      <FIELD2 Name="k_S077">돈이면 다돼요.</FIELD2>
      <DESC>
      </DESC>
    </CONTENT>
    <CONTENT No="S078" Type="" Group="10">
      <FIELD1 Name="e_S078">Most likely.</FIELD1>
      <FIELD2 Name="k_S078">아마도 그럴 것입니다</FIELD2>
      <DESC>
      </DESC>
    </CONTENT>
    <CONTENT No="S079" Type="" Group="10">
      <FIELD1 Name="e_S079">Never better.</FIELD1>
      <FIELD2 Name="k_S079">아주 좋아요. 최고에요.</FIELD2>
      <DESC>
      </DESC>
    </CONTENT>
    <CONTENT No="S080" Type="" Group="10">
      <FIELD1 Name="e_S080">Never too late.</FIELD1>
      <FIELD2 Name="k_S080">너무 늦었다고 생각하지 마</FIELD2>
      <DESC>
      </DESC>
    </CONTENT>
    <CONTENT No="S081" Type="" Group="10">
      <FIELD1 Name="e_S081">No wonder.</FIELD1>
      <FIELD2 Name="k_S081">어쩐지~</FIELD2>
      <DESC>
      </DESC>
    </CONTENT>
    <CONTENT No="S082" Type="" Group="10">
      <FIELD1 Name="e_S082">Once in a blue moon.</FIELD1>
      <FIELD2 Name="k_S082">아주 가끔요</FIELD2>
      <DESC>
      </DESC>
    </CONTENT>
    <CONTENT No="S083" Type="" Group="10">
      <FIELD1 Name="e_S083">Same here.</FIELD1>
      <FIELD2 Name="k_S083">저도 동감입니다</FIELD2>
      <DESC>I feel the same way. 와도 비슷한 느낌</DESC>
    </CONTENT>
    <CONTENT No="S084" Type="" Group="10">
      <FIELD1 Name="e_S084">Shame on you.</FIELD1>
      <FIELD2 Name="k_S084">쪽 팔린 줄 알아!</FIELD2>
      <DESC>(부끄러운줄 알아. 거의 정중한 욕입니다)</DESC>
    </CONTENT>
    <CONTENT No="S085" Type="" Group="10">
      <FIELD1 Name="e_S085">Something's fishy.</FIELD1>
      <FIELD2 Name="k_S085">뭔가 수상한데 (뭔가 냄새가 나)</FIELD2>
      <DESC>
      </DESC>
    </CONTENT>
    <CONTENT No="S086" Type="" Group="10">
      <FIELD1 Name="e_S086">Take a guess. (Can you guess?)</FIELD1>
      <FIELD2 Name="k_S086">맞춰봐요</FIELD2>
      <DESC>Guess what</DESC>
    </CONTENT>
    <CONTENT No="S087" Type="" Group="10">
      <FIELD1 Name="e_S087">Take care!</FIELD1>
      <FIELD2 Name="k_S087">잘가~~</FIELD2>
      <DESC>(원 뜻과 달리 헤어질 때 잘가라는 말고 가장 많이 씁니다. 병실에서야 ‘몸조리 잘해'가 되겠지만)</DESC>
    </CONTENT>
    <CONTENT No="S088" Type="" Group="10">
      <FIELD1 Name="e_S088">Take my word for it.</FIELD1>
      <FIELD2 Name="k_S088">그건 내 말을 믿어봐</FIELD2>
      <DESC>
      </DESC>
    </CONTENT>
    <CONTENT No="S089" Type="" Group="10">
      <FIELD1 Name="e_S089">Take your time.</FIELD1>
      <FIELD2 Name="k_S089">천천히 하세요</FIELD2>
      <DESC>
      </DESC>
    </CONTENT>
    <CONTENT No="S090" Type="" Group="10">
      <FIELD1 Name="e_S090">That depends.</FIELD1>
      <FIELD2 Name="k_S090">경우에 따라 다르죠.</FIELD2>
      <DESC>
      </DESC>
    </CONTENT>
    <CONTENT No="S091" Type="" Group="10">
      <FIELD1 Name="e_S091">That happens.</FIELD1>
      <FIELD2 Name="k_S091">그런 일도 있지요</FIELD2>
      <DESC>
      </DESC>
    </CONTENT>
    <CONTENT No="S092" Type="" Group="10">
      <FIELD1 Name="e_S092">That's a steal.</FIELD1>
      <FIELD2 Name="k_S092">거저 가져 가는 셈이지요</FIELD2>
      <DESC>(쌉니다, 공짜나 다름 없어요)</DESC>
    </CONTENT>
    <CONTENT No="S093" Type="" Group="10">
      <FIELD1 Name="e_S093">That's the way to go.</FIELD1>
      <FIELD2 Name="k_S093">그래 그렇게 하는거지. (바로 그거죠)</FIELD2>
      <DESC>
      </DESC>
    </CONTENT>
    <CONTENT No="S094" Type="" Group="10">
      <FIELD1 Name="e_S094">That's what I mean.</FIELD1>
      <FIELD2 Name="k_S094">내 말이!</FIELD2>
      <DESC>(그게 내가 말하고자 하는 바야)</DESC>
    </CONTENT>
    <CONTENT No="S095" Type="" Group="10">
      <FIELD1 Name="e_S095">Time will tell.</FIELD1>
      <FIELD2 Name="k_S095">시간이 해결해 줄거예요</FIELD2>
      <DESC>(시간이 말해 줄것입니다)</DESC>
    </CONTENT>
    <CONTENT No="S096" Type="" Group="10">
      <FIELD1 Name="e_S096">Time flies.</FIELD1>
      <FIELD2 Name="k_S096">시간 빨리 가네요.</FIELD2>
      <DESC>
      </DESC>
    </CONTENT>
    <CONTENT No="S097" Type="" Group="10">
      <FIELD1 Name="e_S097">To the best of my knowledge~</FIELD1>
      <FIELD2 Name="k_S097">적어도 내가 알기로는~</FIELD2>
      <DESC>as far as I know</DESC>
    </CONTENT>
    <CONTENT No="S098" Type="" Group="10">
      <FIELD1 Name="e_S098">We are in the same boat.</FIELD1>
      <FIELD2 Name="k_S098">우리는 같은 처지에요.</FIELD2>
      <DESC>
      </DESC>
    </CONTENT>
    <CONTENT No="S099" Type="" Group="10">
      <FIELD1 Name="e_S099">What a nerve!</FIELD1>
      <FIELD2 Name="k_S099">뻔뻔 하군요</FIELD2>
      <DESC>How shameless, quite bold(대담/뻔뻔)
 (간댕이가 부었군)</DESC>
    </CONTENT>
    <CONTENT No="S100" Type="" Group="10">
      <FIELD1 Name="e_S100">What a relief!</FIELD1>
      <FIELD2 Name="k_S100">이제 맘이 놓인다</FIELD2>
      <DESC>That's a relief</DESC>
    </CONTENT>
    <CONTENT No="S101" Type="" Group="10">
      <FIELD1 Name="e_S101">What makes you say that?</FIELD1>
      <FIELD2 Name="k_S101">무슨 근거로 그렇게 말하세요?</FIELD2>
      <DESC>
      </DESC>
    </CONTENT>
    <CONTENT No="S102" Type="" Group="10">
      <FIELD1 Name="e_S102">Who knows?</FIELD1>
      <FIELD2 Name="k_S102">누가 알겠어</FIELD2>
      <DESC>
      </DESC>
    </CONTENT>
    <CONTENT No="S103" Type="" Group="10">
      <FIELD1 Name="e_S103">Who's calling?</FIELD1>
      <FIELD2 Name="k_S103">(전화를 받으면서) 누구시지요?</FIELD2>
      <DESC>
      </DESC>
    </CONTENT>
    <CONTENT No="S104" Type="" Group="10">
      <FIELD1 Name="e_S104">With pleasure.</FIELD1>
      <FIELD2 Name="k_S104">기꺼이</FIELD2>
      <DESC>
      </DESC>
    </CONTENT>
    <CONTENT No="S105" Type="" Group="10">
      <FIELD1 Name="e_S105">You are driving me crazy.</FIELD1>
      <FIELD2 Name="k_S105">절 완전 짜증나게 하시네요</FIELD2>
      <DESC>
      </DESC>
    </CONTENT>
    <CONTENT No="S106" Type="" Group="10">
      <FIELD1 Name="e_S106">You cannot fool me.</FIELD1>
      <FIELD2 Name="k_S106">날 속일 수 있다고 생각하지 마</FIELD2>
      <DESC>
      </DESC>
    </CONTENT>
    <CONTENT No="S107" Type="" Group="10">
      <FIELD1 Name="e_S107">You can say that again.</FIELD1>
      <FIELD2 Name="k_S107">지당한 말씀이지요</FIELD2>
      <DESC>Same here 와 비슷</DESC>
    </CONTENT>
    <CONTENT No="S108" Type="" Group="10">
      <FIELD1 Name="e_S108">You flatter me.</FIELD1>
      <FIELD2 Name="k_S108">저를 우쭐하게 만들어주시네요 (보통은 감사의 의미)</FIELD2>
      <DESC>I am flattered.</DESC>
    </CONTENT>
    <CONTENT No="S109" Type="" Group="10">
      <FIELD1 Name="e_S109">You name it.</FIELD1>
      <FIELD2 Name="k_S109">말씀만 하세요</FIELD2>
      <DESC>
      </DESC>
    </CONTENT>
    <CONTENT No="S110" Type="" Group="10">
      <FIELD1 Name="e_S110">You stay out of it.</FIELD1>
      <FIELD2 Name="k_S110">넌 이것에 끼어 들지 마</FIELD2>
      <DESC>
      </DESC>
    </CONTENT>
    <CONTENT No="S111" Type="" Group="10">
      <FIELD1 Name="e_S111">You went too far this time.</FIELD1>
      <FIELD2 Name="k_S111">이번엔 좀 과하셨어요</FIELD2>
      <DESC>too much.</DESC>
    </CONTENT>
    <CONTENT No="S112" Type="" Group="10">
      <FIELD1 Name="e_S112">None of your business.</FIELD1>
      <FIELD2 Name="k_S112">네 알바가 아니야</FIELD2>
      <DESC>
      </DESC>
    </CONTENT>
    <CONTENT No="S113" Type="" Group="10">
      <FIELD1 Name="e_S113">I got blacked out yesterday.</FIELD1>
      <FIELD2 Name="k_S113">어제 필름이 끊겼어</FIELD2>
      <DESC>
      </DESC>
    </CONTENT>
    <CONTENT No="S114" Type="" Group="10">
      <FIELD1 Name="e_S114">He deserves it.</FIELD1>
      <FIELD2 Name="k_S114">그 사람 그거 참 잘~ 됐다(그게당연하다). 쌤통이다</FIELD2>
      <DESC>
      </DESC>
    </CONTENT>
    <CONTENT No="S115" Type="" Group="10">
      <FIELD1 Name="e_S115">Okay, You are the boss!</FIELD1>
      <FIELD2 Name="k_S115">너 잘났다.</FIELD2>
      <DESC>(니 팔뚝 굵다)</DESC>
    </CONTENT>
    <CONTENT No="S116" Type="" Group="10">
      <FIELD1 Name="e_S116">Suit yourself.</FIELD1>
      <FIELD2 Name="k_S116">니 맘대로 하세요</FIELD2>
      <DESC>
      </DESC>
    </CONTENT>
    <CONTENT No="S117" Type="" Group="10">
      <FIELD1 Name="e_S117">That place rocks! That place kicks!</FIELD1>
      <FIELD2 Name="k_S117">거기 물 좋다</FIELD2>
      <DESC>
      </DESC>
    </CONTENT>
    <CONTENT No="S118" Type="" Group="10">
      <FIELD1 Name="e_S118">It sucks!</FIELD1>
      <FIELD2 Name="k_S118">그거 별로야</FIELD2>
      <DESC>
      </DESC>
    </CONTENT>
    <CONTENT No="S119" Type="" Group="10">
      <FIELD1 Name="e_S119">Put yourself in my shoes.</FIELD1>
      <FIELD2 Name="k_S119">너도 내 입장이 되어봐</FIELD2>
      <DESC>
      </DESC>
    </CONTENT>
    <CONTENT No="S120" Type="" Group="10">
      <FIELD1 Name="e_S120">Come on, what are friends for?</FIELD1>
      <FIELD2 Name="k_S120">야, 친구 좋다는 게 뭐야?</FIELD2>
      <DESC>
      </DESC>
    </CONTENT>
    <CONTENT No="S121" Type="" Group="10">
      <FIELD1 Name="e_S121">There's nothing to be sorry about.</FIELD1>
      <FIELD2 Name="k_S121">미안해 할 것까지는 없어.</FIELD2>
      <DESC>
      </DESC>
    </CONTENT>
    <CONTENT No="S122" Type="" Group="10">
      <FIELD1 Name="e_S122">You won't be disappointed!</FIELD1>
      <FIELD2 Name="k_S122">섭섭(실망)하지않게해드리겠습니다!</FIELD2>
      <DESC>
      </DESC>
    </CONTENT>
    <CONTENT No="S123" Type="" Group="10">
      <FIELD1 Name="e_S123">That's what you always do.</FIELD1>
      <FIELD2 Name="k_S123">니가 하는 일이 다 그렇지 뭐</FIELD2>
      <DESC>
      </DESC>
    </CONTENT>
    <CONTENT No="S124" Type="" Group="10">
      <FIELD1 Name="e_S124">Consider your surroundings, you fool.</FIELD1>
      <FIELD2 Name="k_S124">분위기 파악 좀 해라, 인간아</FIELD2>
      <DESC>
      </DESC>
    </CONTENT>
    <CONTENT No="S125" Type="" Group="10">
      <FIELD1 Name="e_S125">Let's stop playing word games</FIELD1>
      <FIELD2 Name="k_S125">말장난 그만 합시다.</FIELD2>
      <DESC>Do I look easy?</DESC>
    </CONTENT>
    <CONTENT No="S126" Type="" Group="10">
      <FIELD1 Name="e_S126">Do I look like I am easy?</FIELD1>
      <FIELD2 Name="k_S126">내가 만만하게 보여?</FIELD2>
      <DESC>
      </DESC>
    </CONTENT>
    <CONTENT No="S127" Type="" Group="10">
      <FIELD1 Name="e_S127">I feel heavy</FIELD1>
      <FIELD2 Name="k_S127">몸이 찌뿌둥하다</FIELD2>
      <DESC>
      </DESC>
    </CONTENT>
    <CONTENT No="S128" Type="" Group="10">
      <FIELD1 Name="e_S128">Don't get me wrong.</FIELD1>
      <FIELD2 Name="k_S128">오해 하지 마세요</FIELD2>
      <DESC>Speechless, ridiculous. Don't be ridiculous.</DESC>
    </CONTENT>
    <CONTENT No="S129" Type="" Group="10">
      <FIELD1 Name="e_S129">It's so outrageous I can't say a word</FIELD1>
      <FIELD2 Name="k_S129">기가막혀 말이 안나오네.</FIELD2>
      <DESC>Whatever you want! You are the boss.</DESC>
    </CONTENT>
    <CONTENT No="S130" Type="" Group="10">
      <FIELD1 Name="e_S130">You are dead meat!</FIELD1>
      <FIELD2 Name="k_S130">넌 이제 죽었어</FIELD2>
      <DESC>
      </DESC>
    </CONTENT>
    <CONTENT No="S131" Type="" Group="10">
      <FIELD1 Name="e_S131">Sue me!</FIELD1>
      <FIELD2 Name="k_S131">배째</FIELD2>
      <DESC>
      </DESC>
    </CONTENT>
    <CONTENT No="S132" Type="" Group="10">
      <FIELD1 Name="e_S132">My head is about to open</FIELD1>
      <FIELD2 Name="k_S132">머리뚜껑이 열렸다.</FIELD2>
      <DESC>
      </DESC>
    </CONTENT>
    <CONTENT No="S133" Type="" Group="10">
      <FIELD1 Name="e_S133">I don't feel well(good) about it, either.</FIELD1>
      <FIELD2 Name="k_S133">나도 맘이 편하지는 않아.</FIELD2>
      <DESC>
      </DESC>
    </CONTENT>
    <CONTENT No="S134" Type="" Group="10">
      <FIELD1 Name="e_S134">I don't feel like doing it</FIELD1>
      <FIELD2 Name="k_S134">그다지 썩 내키지는 않는데.</FIELD2>
      <DESC>
      </DESC>
    </CONTENT>
    <CONTENT No="S135" Type="" Group="10">
      <FIELD1 Name="e_S135">It's not as good as I thought (expected)</FIELD1>
      <FIELD2 Name="k_S135">생각보다 '별로'인데...</FIELD2>
      <DESC>
      </DESC>
    </CONTENT>
    <CONTENT No="S136" Type="" Group="10">
      <FIELD1 Name="e_S136">My whole body aches.</FIELD1>
      <FIELD2 Name="k_S136">몸살에 걸려 온몸이 쑤신다.</FIELD2>
      <DESC>
      </DESC>
    </CONTENT>
    <CONTENT No="S137" Type="" Group="10">
      <FIELD1 Name="e_S137">To be exact, To be specific</FIELD1>
      <FIELD2 Name="k_S137">정확하게 말하자면</FIELD2>
      <DESC>
      </DESC>
    </CONTENT>
    <CONTENT No="S138" Type="" Group="10">
      <FIELD1 Name="e_S138">To be honest</FIELD1>
      <FIELD2 Name="k_S138">솔직히 말하자면</FIELD2>
      <DESC>Frankly speaking</DESC>
    </CONTENT>
    <CONTENT No="S139" Type="" Group="10">
      <FIELD1 Name="e_S139">I wasn't born yesterday</FIELD1>
      <FIELD2 Name="k_S139">세상물정에 어둡지 않아요</FIELD2>
      <DESC>
      </DESC>
    </CONTENT>
    <CONTENT No="S140" Type="" Group="10">
      <FIELD1 Name="e_S140">I'd love to but~</FIELD1>
      <FIELD2 Name="k_S140">그러고 싶지만(거절을 위한)</FIELD2>
      <DESC>
      </DESC>
    </CONTENT>
    <CONTENT No="S141" Type="" Group="10">
      <FIELD1 Name="e_S141">figure it out yourself</FIELD1>
      <FIELD2 Name="k_S141">니가 알아서 좀 해</FIELD2>
      <DESC>
      </DESC>
    </CONTENT>
    <CONTENT No="S142" Type="" Group="10">
      <FIELD1 Name="e_S142">Brace yourself</FIELD1>
      <FIELD2 Name="k_S142">마음 준비 단단히 해</FIELD2>
      <DESC>
      </DESC>
    </CONTENT>
    <CONTENT No="S143" Type="" Group="10">
      <FIELD1 Name="e_S143">Let's get this straight,</FIELD1>
      <FIELD2 Name="k_S143">이건 확실히 짚고 넘어갑시다</FIELD2>
      <DESC>Let's make it clear.</DESC>
    </CONTENT>
    <CONTENT No="S144" Type="" Group="10">
      <FIELD1 Name="e_S144">just in case</FIELD1>
      <FIELD2 Name="k_S144">만약을 대비하여..</FIELD2>
      <DESC>
      </DESC>
    </CONTENT>
    <CONTENT No="S145" Type="" Group="10">
      <FIELD1 Name="e_S145">Look! Who's talking.</FIELD1>
      <FIELD2 Name="k_S145">사돈 남말하네</FIELD2>
      <DESC>
      </DESC>
    </CONTENT>
    <CONTENT No="S146" Type="" Group="10">
      <FIELD1 Name="e_S146">speaking of the devil</FIELD1>
      <FIELD2 Name="k_S146">호랑도 제말하면 온다더니</FIELD2>
      <DESC>
      </DESC>
    </CONTENT>
    <CONTENT No="S147" Type="" Group="10">
      <FIELD1 Name="e_S147">speaking of which</FIELD1>
      <FIELD2 Name="k_S147">말나온 김에</FIELD2>
      <DESC>speaking of that(it)</DESC>
    </CONTENT>
    <CONTENT No="S148" Type="" Group="10">
      <FIELD1 Name="e_S148">I was mistaken.</FIELD1>
      <FIELD2 Name="k_S148">내가 착각했네</FIELD2>
      <DESC>
      </DESC>
    </CONTENT>
    <CONTENT No="S149" Type="" Group="10">
      <FIELD1 Name="e_S149">What a coincidence!</FIELD1>
      <FIELD2 Name="k_S149">이런 우연이!</FIELD2>
      <DESC>
      </DESC>
    </CONTENT>
    <CONTENT No="S150" Type="" Group="10">
      <FIELD1 Name="e_S150">There's nothing to lose.</FIELD1>
      <FIELD2 Name="k_S150">밑져야 본전</FIELD2>
      <DESC>
      </DESC>
    </CONTENT>
    <CONTENT No="S151" Type="" Group="10">
      <FIELD1 Name="e_S151">It wouldn't hurt to try.</FIELD1>
      <FIELD2 Name="k_S151">해보는 것도 나쁘지 않아.</FIELD2>
      <DESC>
      </DESC>
    </CONTENT>
    <CONTENT No="S152" Type="" Group="10">
      <FIELD1 Name="e_S152">I told you.</FIELD1>
      <FIELD2 Name="k_S152">내가 말했잖아.</FIELD2>
      <DESC>told you so.</DESC>
    </CONTENT>
    <CONTENT No="S153" Type="" Group="10">
      <FIELD1 Name="e_S153">Don't beat around the bush.</FIELD1>
      <FIELD2 Name="k_S153">빙빙 돌려말하지 마!</FIELD2>
      <DESC>
      </DESC>
    </CONTENT>
  </CONTENTS>
</ROOT>